report_manager/__init__.py
report_manager/report_manager.py
report_manager/version.py
report_manager-0.8.0.dist-info/LICENSE
report_manager-0.8.0.dist-info/METADATA
report_manager-0.8.0.dist-info/WHEEL
report_manager-0.8.0.dist-info/entry_points.txt
report_manager-0.8.0.dist-info/top_level.txt
report_manager-0.8.0.dist-info/RECORD
