Metadata-Version: 2.1
Name: report-manager
Version: 0.8.0
Summary: Manage your reports
Home-page: https://github.com/Knuckles-Team/report-manager
Author: Audel Rouhi
Author-email: knucklessg1@gmail.com
License: Unlicense
Platform: UNKNOWN
Classifier: Development Status :: 5 - Production/Stable
Classifier: License :: Public Domain
Classifier: Environment :: Console
Classifier: Operating System :: POSIX :: Linux
Classifier: Programming Language :: Python :: 3.8
Classifier: Programming Language :: Python :: 3.9
Classifier: Programming Language :: Python :: 3.10
Classifier: Programming Language :: Python :: 3.11
License-File: LICENSE
Requires-Dist: ipywidgets (>=8.0.4)
Requires-Dist: matplotlib (>=3.6.2)
Requires-Dist: numpy (>=1.23.5)
Requires-Dist: pandas (>=1.5.2)
Requires-Dist: scikit-learn (>=1.2.0)
Requires-Dist: scipy (>=1.9.3)
Requires-Dist: tabulate (>=0.9.0)
Requires-Dist: xlsxwriter (>=3.0.3)
Requires-Dist: ydata-profiling (>=4.1.2)
